setup.py
salure_helpers/jira/__init__.py
salure_helpers/jira/jira.py
salure_helpers/jira/tempo.py
salure_helpers_jira.egg-info/PKG-INFO
salure_helpers_jira.egg-info/SOURCES.txt
salure_helpers_jira.egg-info/dependency_links.txt
salure_helpers_jira.egg-info/not-zip-safe
salure_helpers_jira.egg-info/requires.txt
salure_helpers_jira.egg-info/top_level.txt