Metadata-Version: 1.0
Name: salure-helpers-jira
Version: 1.1.2
Summary: JIRA wrapper from Salure
Home-page: UNKNOWN
Author: D&A Salure
Author-email: support@salureconnnect.com
License: Salure License
Platform: UNKNOWN
